oomnitza_rule_checker/__init__.py
oomnitza_rule_checker/checker.py
oomnitza_rule_checker/helpers.py
oomnitza_rule_checker/py.typed
oomnitza_rule_checker-0.3.4.dist-info/LICENSE
oomnitza_rule_checker-0.3.4.dist-info/METADATA
oomnitza_rule_checker-0.3.4.dist-info/WHEEL
oomnitza_rule_checker-0.3.4.dist-info/top_level.txt
oomnitza_rule_checker-0.3.4.dist-info/RECORD
