Metadata-Version: 2.1
Name: oomnitza_rule_checker
Version: 0.3.4
Summary: Contains reusable logic to check Oomnitza begin criteria for objects
Home-page: https://bitbucket.org/oomnitza/oomnitza-rule-checker
Author: Oomnitza, Vital Kudzelka and others
Author-email: vital.kudzelka@oomnitza.com
License: MIT
Keywords: oomnitza
Platform: unix
Platform: linux
Platform: osx
Classifier: Development Status :: 2 - Pre-Alpha
Classifier: Intended Audience :: Developers
Classifier: License :: OSI Approved :: MIT License
Classifier: Natural Language :: English
Classifier: Programming Language :: Python :: 3
Classifier: Programming Language :: Python :: 3 :: Only
Classifier: Programming Language :: Python :: 3.6
Classifier: Programming Language :: Python :: 3.7
Classifier: Programming Language :: Python :: 3.8
Classifier: Programming Language :: Python :: 3.9
Classifier: Programming Language :: Python :: 3.10
Classifier: Topic :: Software Development :: Libraries
Classifier: Topic :: Utilities
Requires-Python: >=3.6
License-File: LICENSE
Requires-Dist: arrow ==0.12.1
Provides-Extra: tests
Requires-Dist: pytest >=3 ; extra == 'tests'
Requires-Dist: pytest-lazy-fixture >=0.6.3 ; extra == 'tests'
Requires-Dist: pytest-cov >=2 ; extra == 'tests'
